{
  "synth_mode": "sum",
  "synth_tag": "sum-auto",
  "roi": {
    "x_range": [
      20,
      90
    ],
    "y_range": [
      190,
      260
    ],
    "n": 4900
  },
  "metrics": [
    "pearson",
    "spearman",
    "kendall",
    "mi",
    "dcorr",
    "hsic",
    "pp_spatial"
  ],
  "elements": [
    "Al",
    "C",
    "Ca",
    "Fe",
    "K",
    "Mg",
    "Mn",
    "Na",
    "O",
    "P",
    "S",
    "Si",
    "Ti",
    "V"
  ],
  "rgb_elements": null,
  "weights": null,
  "rankings": {
    "pearson": [
      {
        "dim": 469,
        "score": -0.1269636794192189
      },
      {
        "dim": 235,
        "score": 0.12211516862940694
      },
      {
        "dim": 331,
        "score": 0.12187128757503676
      }
    ],
    "spearman": [
      {
        "dim": 404,
        "score": -0.12874799839307965
      },
      {
        "dim": 103,
        "score": 0.12261828153076755
      },
      {
        "dim": 384,
        "score": -0.12063997050649326
      }
    ],
    "kendall": [
      {
        "dim": 404,
        "score": -0.08628751419764243
      },
      {
        "dim": 103,
        "score": 0.0818203183524523
      },
      {
        "dim": 384,
        "score": -0.08088375342392226
      }
    ],
    "mi": [
      {
        "dim": 251,
        "score": 0.025531622704593637
      },
      {
        "dim": 387,
        "score": 0.023853101906690988
      },
      {
        "dim": 151,
        "score": 0.02131065395115428
      }
    ],
    "dcorr": [
      {
        "dim": 469,
        "score": 0.12453882497782616
      },
      {
        "dim": 404,
        "score": 0.12333914923369355
      },
      {
        "dim": 251,
        "score": 0.120095795144577
      }
    ],
    "hsic": [
      {
        "dim": 469,
        "score": 0.0010284589186675475
      },
      {
        "dim": 103,
        "score": 0.0008917278748923755
      },
      {
        "dim": 404,
        "score": 0.0008873542184995398
      }
    ],
    "pp_spatial": [
      {
        "dim": 384,
        "score": -0.1063584030174975
      },
      {
        "dim": 331,
        "score": 0.10498496656668471
      },
      {
        "dim": 469,
        "score": -0.09812954235245044
      }
    ]
  }
}